lark_shell.py
lark_shell-0.1.3.dist-info/entry_points.txt
lark_shell-0.1.3.dist-info/LICENSE
lark_shell-0.1.3.dist-info/WHEEL
lark_shell-0.1.3.dist-info/METADATA
lark_shell-0.1.3.dist-info/RECORD
