Metadata-Version: 2.1
Name: lark-shell
Version: 0.1.3
Summary: A terminal version of the online Lark IDE
Home-page: https://github.com/ThatXliner/lark_shell/
License: GPL-3.0-or-later
Keywords: lark,lark-parser,urwid,tool,terminal
Author: Bryan Hu
Author-email: bryan.hu.2020@gmail.com
Requires-Python: >=3.6,<4.0
Classifier: Development Status :: 4 - Beta
Classifier: Environment :: Console
Classifier: Intended Audience :: Developers
Classifier: License :: OSI Approved :: GNU General Public License v3 or later (GPLv3+)
Classifier: Natural Language :: English
Classifier: Operating System :: OS Independent
Classifier: Operating System :: POSIX
Classifier: Programming Language :: Python :: 3
Classifier: Programming Language :: Python :: 3.6
Classifier: Programming Language :: Python :: 3.7
Classifier: Programming Language :: Python :: 3.8
Classifier: Programming Language :: Python :: 3.9
Classifier: Programming Language :: Python :: Implementation :: CPython
Classifier: Programming Language :: Python :: Implementation :: PyPy
Classifier: Topic :: Utilities
Classifier: Typing :: Typed
Requires-Dist: lark-parser (>=0.8.0,<1.0.0)
Requires-Dist: urwid (>=2.1.2,<3.0.0)
Project-URL: Bug Tracker, https://github.com/ThatXliner/lark_shell/issues
Project-URL: Source Code, https://github.com/ThatXliner/lark_shell
Project-URL: Say Thanks! , https://saythanks.io/to/bryan.hu.2020@gmail.com
